README.md
aioflake.py
setup.cfg
setup.py
aioflake.egg-info/PKG-INFO
aioflake.egg-info/SOURCES.txt
aioflake.egg-info/dependency_links.txt
aioflake.egg-info/top_level.txt