Metadata-Version: 1.2
Name: aioflake
Version: 0.1.1
Summary: Unique id generator inspired by twitter's snowflake.
Home-page: https://github.com/guyingbo/aioflake
Author: Yingbo Gu
Author-email: tensiongyb@gmail.com
License: MIT
Platform: UNKNOWN
Classifier: Programming Language :: Python :: 3.5
Classifier: Programming Language :: Python :: 3.6
Classifier: Intended Audience :: Developers
Requires-Python: >=3.5
